[{"name":"s_vi","value":"[CS]v1|339449A6D50BE8DC-600000EBC0EBA2ED[CE]","domain":".apple.com","path":"/","expires":1730714201.418783,"size":48,"httpOnly":false,"secure":true,"session":false,"sameSite":"None","priority":"Medium","sameParty":false,"sourceScheme":"Secure"},{"name":"as_pcts","value":"G6lLq_stkUWEAbm7mqj5h:+1OUgIqToVKwzjboHC-shUNBUGZ89h:YWOsBuBvo8P4AhcJsCaABpYxZ+9huFRROQTAPLXIAz3W-znQCx:RiFxAC617PvcnpZ+PyyILixNNKzDP_y9lE8rK3OwapCtQ6aKvQ4Wsj:SOwDoaBSpjTC_heSXGaAekSg8SB7OHsGxb9zuW-bYD16c9PyzBUxxfj0:LPzH2FNRrI","domain":".apple.com","path":"/","expires":-1,"size":233,"httpOnly":true,"secure":true,"session":true,"priority":"Medium","sameParty":false,"sourceScheme":"Secure"},{"name":"as_dc","value":"ucp6","domain":".apple.com","path":"/","expires":1730719601.618034,"size":9,"httpOnly":false,"secure":true,"session":false,"priority":"Medium","sameParty":false,"sourceScheme":"Secure"},{"name":"mbox","value":"session#8352f5db84924c0aa1f7988705475797#1730714257|PC#8352f5db84924c0aa1f7988705475797.37_0#1730714198","domain":".apple.com","path":"/","expires":1730714257,"size":107,"httpOnly":false,"secure":false,"session":false,"priority":"Medium","sameParty":false,"sourceScheme":"Secure"},{"name":"s_cc","value":"true","domain":".apple.com","path":"/","expires":-1,"size":8,"httpOnly":false,"secure":true,"session":true,"priority":"Medium","sameParty":false,"sourceScheme":"Secure"},{"name":"s_fid","value":"180AA407C0271E06-031C6E4E4DCEE3BE","domain":".apple.com","path":"/","expires":1730714201,"size":38,"httpOnly":false,"secure":true,"session":false,"priority":"Medium","sameParty":false,"sourceScheme":"Secure"},{"name":"dssid2","value":"96ffbea2-d865-4e6d-a63c-b500c3e198db","domain":".apple.com","path":"/","expires":1762248401.617627,"size":42,"httpOnly":true,"secure":true,"session":false,"priority":"Medium","sameParty":false,"sourceScheme":"Secure"},{"name":"s_sq","value":"%5B%5BB%5D%5D","domain":".apple.com","path":"/","expires":-1,"size":17,"httpOnly":false,"secure":true,"session":true,"priority":"Medium","sameParty":false,"sourceScheme":"Secure"},{"name":"dssf","value":"1","domain":".apple.com","path":"/","expires":1762248401.617883,"size":5,"httpOnly":true,"secure":true,"session":false,"priority":"Medium","sameParty":false,"sourceScheme":"Secure"},{"name":"at_check","value":"true","domain":".apple.com","path":"/","expires":-1,"size":12,"httpOnly":false,"secure":false,"session":true,"priority":"Medium","sameParty":false,"sourceScheme":"Secure"},{"name":"mk_epub","value":"%7B%22btuid%22%3A%228p16ja%22%2C%22prop57%22%3A%22www.es.homepage%22%7D","domain":".apple.com","path":"/","expires":-1,"size":78,"httpOnly":false,"secure":true,"session":true,"priority":"Medium","sameParty":false,"sourceScheme":"Secure"},{"name":"geo","value":"ES","domain":".apple.com","path":"/","expires":-1,"size":5,"httpOnly":false,"secure":false,"session":true,"priority":"Medium","sameParty":false,"sourceScheme":"Secure"}]