[{"name":"cto_bundle","value":"3Zy0DF9seFlkTHBncGF3WGRqRE1vZGhYWlMzdCUyQk9iYVQlMkJwN3lmcDZmaUhpJTJGR0FXdzJ0bTdINmQ3aVJNcTIwSGpSNmt6NVhFRGlkeEoyTmRWS1JKWDJNa29nanJWOXMlMkJMbzdYdDhoUkdMUEEzZnVmclZmbU1IRUpvUHVlVUpSVjVLSFh3","domain":".samsung.com","path":"/","expires":1764454411,"size":198,"httpOnly":false,"secure":false,"session":false,"priority":"Medium","sameParty":false,"sourceScheme":"Secure"},{"name":"_cs_s","value":"1.0.0.9.1730292210554","domain":".samsung.com","path":"/","expires":1730292210,"size":26,"httpOnly":false,"secure":false,"session":false,"sameSite":"Lax","priority":"Medium","sameParty":false,"sourceScheme":"Secure"},{"name":"_cs_cvars","value":"%7B%221%22%3A%5B%22Page%20Track%22%2C%22home%22%5D%7D","domain":".samsung.com","path":"/","expires":-1,"size":62,"httpOnly":false,"secure":false,"session":true,"sameSite":"Lax","priority":"Medium","sameParty":false,"sourceScheme":"Secure"},{"name":"_ga_WL7LMPQ7V8","value":"GS1.1.1730290407.1.0.1730290410.0.0.2042622317","domain":".samsung.com","path":"/","expires":1764850410.170495,"size":60,"httpOnly":false,"secure":false,"session":false,"priority":"Medium","sameParty":false,"sourceScheme":"Secure"},{"name":"_bkrmkt","value":"%7B%22pageview%22%3A-4092911288%7D","domain":"www.samsung.com","path":"/","expires":1730294009.492133,"size":41,"httpOnly":false,"secure":false,"session":false,"priority":"Medium","sameParty":false,"sourceScheme":"Secure"},{"name":"aam-segment","value":"id%3D11644241","domain":"www.samsung.com","path":"/","expires":1732882409,"size":24,"httpOnly":false,"secure":true,"session":false,"sameSite":"None","priority":"Medium","sameParty":false,"sourceScheme":"Secure"},{"name":"dicbo_id","value":"%7B%22dicbo_fetch%22%3A1730290408636%7D","domain":"www.samsung.com","path":"/","expires":1730290708,"size":47,"httpOnly":false,"secure":false,"session":false,"priority":"Medium","sameParty":false,"sourceScheme":"Secure"},{"name":"FPGSID","value":"1.1730290408.1730290408.G-WL7LMPQ7V8.az-kCTb3-j1FGUVCK7Xx9A","domain":".samsung.com","path":"/","expires":1730292208.291059,"size":65,"httpOnly":false,"secure":true,"session":false,"sameSite":"Strict","priority":"Medium","sameParty":false,"sourceScheme":"Secure"},{"name":"FPAU","value":"1.2.1453481741.1730290408","domain":".samsung.com","path":"/","expires":1738066408.290975,"size":29,"httpOnly":false,"secure":true,"session":false,"priority":"Medium","sameParty":false,"sourceScheme":"Secure"},{"name":"_fbp","value":"fb.1.1730290408835.846834537612618928","domain":".samsung.com","path":"/","expires":1738066409,"size":41,"httpOnly":false,"secure":false,"session":false,"sameSite":"Lax","priority":"Medium","sameParty":false,"sourceScheme":"Secure"},{"name":"tfpsi","value":"3d9d34aa-59f2-4a58-a073-9762e8b497b1","domain":".samsung.com","path":"/","expires":1730292208.373999,"size":41,"httpOnly":false,"secure":true,"session":false,"sameSite":"None","priority":"Medium","sameParty":false,"sourceScheme":"Secure"},{"name":"_ttp","value":"LSIBRHBT8kl5_ac2q0m8wKWQMnx","domain":".samsung.com","path":"/","expires":1738066407,"size":31,"httpOnly":false,"secure":false,"session":false,"priority":"Medium","sameParty":false,"sourceScheme":"Secure"},{"name":"AMCV_35FCB57359006AE20A495EEF%40AdobeOrg","value":"MCMID|90875326949106344184165953142772200066","domain":".samsung.com","path":"/","expires":1763986407,"size":84,"httpOnly":false,"secure":true,"session":false,"sameSite":"None","priority":"Medium","sameParty":false,"sourceScheme":"Secure"},{"name":"_cs_mk_aa","value":"0.8643131509616373_1730290408360","domain":".samsung.com","path":"/","expires":1730292208,"size":41,"httpOnly":false,"secure":true,"session":false,"sameSite":"None","priority":"Medium","sameParty":false,"sourceScheme":"Secure"},{"name":"AMCV_470D362A62188DCD0A495F88%40AdobeOrg","value":"MCMID|71015765027734882414290314353134181729","domain":".samsung.com","path":"/","expires":1763986407,"size":84,"httpOnly":false,"secure":true,"session":false,"sameSite":"None","priority":"Medium","sameParty":false,"sourceScheme":"Secure"},{"name":"_ga","value":"GA1.1.1966086600.1730290407","domain":".samsung.com","path":"/","expires":1764850407.505996,"size":30,"httpOnly":false,"secure":false,"session":false,"priority":"Medium","sameParty":false,"sourceScheme":"Secure"},{"name":"kndctr_35FCB57359006AE20A495EEF_AdobeOrg_consent","value":"general%3Din","domain":".samsung.com","path":"/","expires":1745842407.42725,"size":60,"httpOnly":false,"secure":true,"session":false,"sameSite":"None","priority":"Medium","sameParty":false,"sourceScheme":"Secure"},{"name":"_km","value":"5083ae50-d9b5-45ac-ac58-4f81b2c11d1d","domain":"www.samsung.com","path":"/","expires":1732882410,"size":39,"httpOnly":false,"secure":true,"session":false,"sameSite":"None","priority":"Medium","sameParty":false,"sourceScheme":"Secure"},{"name":"kndctr_35FCB57359006AE20A495EEF_AdobeOrg_cluster","value":"irl1","domain":".samsung.com","path":"/","expires":1730292209.090115,"size":52,"httpOnly":false,"secure":true,"session":false,"sameSite":"None","priority":"Medium","sameParty":false,"sourceScheme":"Secure"},{"name":"kndctr_470D362A62188DCD0A495F88_AdobeOrg_identity","value":"CiY3MTAxNTc2NTAyNzczNDg4MjQxNDI5MDMxNDM1MzEzNDE4MTcyOVIRCNSv4eqtMhgBKgRJUkwxMAKgAd%2Dv4eqtMrABAPAB1K%5Fh6q0y","domain":".samsung.com","path":"/","expires":1764418407.426316,"size":157,"httpOnly":false,"secure":true,"session":false,"sameSite":"None","priority":"Medium","sameParty":false,"sourceScheme":"Secure"},{"name":"s_ppv","value":"es%253Ahome%2C16%2C16%2C600%2C800%2C600%2C1920%2C1080%2C1%2CP","domain":"www.samsung.com","path":"/","expires":-1,"size":66,"httpOnly":false,"secure":false,"session":true,"priority":"Medium","sameParty":false,"sourceScheme":"Secure"},{"name":"kampyleSessionPageCounter","value":"1","domain":"www.samsung.com","path":"/","expires":1761826406,"size":26,"httpOnly":false,"secure":true,"session":false,"sameSite":"None","priority":"Medium","sameParty":false,"sourceScheme":"Secure"},{"name":"kampyleUserSessionsCount","value":"1","domain":"www.samsung.com","path":"/","expires":1761826406,"size":25,"httpOnly":false,"secure":true,"session":false,"sameSite":"None","priority":"Medium","sameParty":false,"sourceScheme":"Secure"},{"name":"_ba_exist","value":"true","domain":".samsung.com","path":"/","expires":1761826404,"size":13,"httpOnly":false,"secure":false,"session":false,"priority":"Medium","sameParty":false,"sourceScheme":"Secure"},{"name":"kampyleUserSession","value":"1730290406657","domain":"www.samsung.com","path":"/","expires":1761826406,"size":31,"httpOnly":false,"secure":true,"session":false,"sameSite":"None","priority":"Medium","sameParty":false,"sourceScheme":"Secure"},{"name":"AKA_A2","value":"A","domain":".samsung.com","path":"/","expires":1730294001.980506,"size":7,"httpOnly":true,"secure":true,"session":false,"priority":"Medium","sameParty":false,"sourceScheme":"Secure"},{"name":"kndctr_470D362A62188DCD0A495F88_AdobeOrg_cluster","value":"irl1","domain":".samsung.com","path":"/","expires":1730292208.460404,"size":52,"httpOnly":false,"secure":true,"session":false,"sameSite":"None","priority":"Medium","sameParty":false,"sourceScheme":"Secure"},{"name":"cmapi_cookie_privacy","value":"permit 1,2,3,4","domain":".samsung.com","path":"/","expires":1764418405,"size":34,"httpOnly":false,"secure":true,"session":false,"sameSite":"None","priority":"Medium","sameParty":false,"sourceScheme":"Secure"},{"name":"_samsungrtetSessId","value":"NTyK0Th","domain":"www.samsung.com","path":"/","expires":1730292204,"size":25,"httpOnly":false,"secure":false,"session":false,"priority":"Medium","sameParty":false,"sourceScheme":"Secure"},{"name":"notice_preferences","value":"3:","domain":".samsung.com","path":"/","expires":1764418405,"size":20,"httpOnly":false,"secure":true,"session":false,"sameSite":"None","priority":"Medium","sameParty":false,"sourceScheme":"Secure"},{"name":"_ba_click","value":"true","domain":"www.samsung.com","path":"/","expires":1730292205,"size":13,"httpOnly":false,"secure":false,"session":false,"priority":"Medium","sameParty":false,"sourceScheme":"Secure"},{"name":"_ba_initial_refer","value":"","domain":".samsung.com","path":"/","expires":1730292204,"size":17,"httpOnly":false,"secure":false,"session":false,"priority":"Medium","sameParty":false,"sourceScheme":"Secure"},{"name":"_samsungrtetSessPageSeq","value":"0","domain":"www.samsung.com","path":"/","expires":1730292204,"size":24,"httpOnly":false,"secure":false,"session":false,"priority":"Medium","sameParty":false,"sourceScheme":"Secure"},{"name":"country_region","value":"CA-ON","domain":".samsung.com","path":"/","expires":-1,"size":19,"httpOnly":false,"secure":false,"session":true,"priority":"Medium","sameParty":false,"sourceScheme":"Secure"},{"name":"mdLogger","value":"false","domain":"www.samsung.com","path":"/","expires":1761826406,"size":13,"httpOnly":false,"secure":true,"session":false,"sameSite":"None","priority":"Medium","sameParty":false,"sourceScheme":"Secure"},{"name":"_beu_cid","value":"__null__","domain":"www.samsung.com","path":"/","expires":1730292204,"size":16,"httpOnly":false,"secure":false,"session":false,"priority":"Medium","sameParty":false,"sourceScheme":"Secure"},{"name":"_beu_utm_term","value":"__null__","domain":"www.samsung.com","path":"/","expires":1730292204,"size":21,"httpOnly":false,"secure":false,"session":false,"priority":"Medium","sameParty":false,"sourceScheme":"Secure"},{"name":"kndctr_35FCB57359006AE20A495EEF_AdobeOrg_identity","value":"CiY5MDg3NTMyNjk0OTEwNjM0NDE4NDE2NTk1MzE0Mjc3MjIwMDA2NlIRCNWv4eqtMhgBKgRJUkwxMAKgAd%2Dv4eqtMrABAPAB1a%5Fh6q0y","domain":".samsung.com","path":"/","expires":1764418407.427166,"size":157,"httpOnly":false,"secure":true,"session":false,"sameSite":"None","priority":"Medium","sameParty":false,"sourceScheme":"Secure"},{"name":"lantern","value":"ad2e10cb-1655-4ca6-87d6-d2c9eb7fa292","domain":".samsung.com","path":"/","expires":1732882408,"size":43,"httpOnly":false,"secure":false,"session":false,"priority":"Medium","sameParty":false,"sourceScheme":"Secure"},{"name":"_beu_utm_medium","value":"__null__","domain":"www.samsung.com","path":"/","expires":1730292204,"size":23,"httpOnly":false,"secure":false,"session":false,"priority":"Medium","sameParty":false,"sourceScheme":"Secure"},{"name":"_bkrmk","value":"%7B%22sid%22%3A763800918899%2C%22chk%22%3A1%2C%22start%22%3A%222024-10-30T12%3A13%3A29.488Z%22%7D","domain":"www.samsung.com","path":"/","expires":1730376809.491393,"size":103,"httpOnly":false,"secure":false,"session":false,"priority":"Medium","sameParty":false,"sourceScheme":"Secure"},{"name":"notice_behavior","value":"implied,eu","domain":".samsung.com","path":"/","expires":-1,"size":25,"httpOnly":false,"secure":true,"session":true,"sameSite":"None","priority":"Medium","sameParty":false,"sourceScheme":"Secure"},{"name":"_beu_utm_source","value":"__null__","domain":"www.samsung.com","path":"/","expires":1730292204,"size":23,"httpOnly":false,"secure":false,"session":false,"priority":"Medium","sameParty":false,"sourceScheme":"Secure"},{"name":"_ba_initial_refer","value":"","domain":"www.samsung.com","path":"/","expires":1730292204,"size":17,"httpOnly":false,"secure":false,"session":false,"priority":"Medium","sameParty":false,"sourceScheme":"Secure"},{"name":"usi_id","value":"cjz88y_1730290409","domain":".samsung.com","path":"/","expires":1732882408,"size":23,"httpOnly":false,"secure":true,"session":false,"sameSite":"None","priority":"Medium","sameParty":false,"sourceScheme":"Secure"},{"name":"_ba_last_url","value":"https%3A%2F%2Fwww.samsung.com%2Fes%2F","domain":".samsung.com","path":"/","expires":1730292204,"size":49,"httpOnly":false,"secure":false,"session":false,"priority":"Medium","sameParty":false,"sourceScheme":"Secure"},{"name":"_cs_id","value":"9490f787-9fb1-adc8-9aad-92ae16808a2a.1730290410.1.1730290410.1730290410.1730283183.1764454410504.1","domain":".samsung.com","path":"/","expires":1764454410,"size":104,"httpOnly":false,"secure":false,"session":false,"sameSite":"Lax","priority":"Medium","sameParty":false,"sourceScheme":"Secure"},{"name":"_tt_enable_cookie","value":"1","domain":".samsung.com","path":"/","expires":1738066407,"size":18,"httpOnly":false,"secure":false,"session":false,"priority":"Medium","sameParty":false,"sourceScheme":"Secure"},{"name":"country_codes","value":"es","domain":".samsung.com","path":"/","expires":-1,"size":15,"httpOnly":false,"secure":false,"session":true,"priority":"Medium","sameParty":false,"sourceScheme":"Secure"},{"name":"_cs_c","value":"0","domain":".samsung.com","path":"/","expires":1764454409,"size":6,"httpOnly":false,"secure":false,"session":false,"sameSite":"Lax","priority":"Medium","sameParty":false,"sourceScheme":"Secure"},{"name":"_ba_page_ct","value":"2024-10-30T12%3A13%3A24.553Z","domain":".samsung.com","path":"/","expires":1730292204,"size":39,"httpOnly":false,"secure":false,"session":false,"priority":"Medium","sameParty":false,"sourceScheme":"Secure"},{"name":"_bkrmku","value":"%7B%22user%22%3A%7B%22language%22%3A%22ES%22%2C%22currency%22%3A%22EUR%22%7D%7D","domain":"www.samsung.com","path":"/","expires":1764418409.490038,"size":86,"httpOnly":false,"secure":false,"session":false,"priority":"Medium","sameParty":false,"sourceScheme":"Secure"},{"name":"notice_gdpr_prefs","value":"0,1,2,3::implied,eu","domain":".samsung.com","path":"/","expires":1764418405,"size":36,"httpOnly":false,"secure":true,"session":false,"sameSite":"None","priority":"Medium","sameParty":false,"sourceScheme":"Secure"},{"name":"directCallFlAA","value":"undefined","domain":".samsung.com","path":"/","expires":-1,"size":23,"httpOnly":false,"secure":false,"session":true,"priority":"Medium","sameParty":false,"sourceScheme":"Secure"},{"name":"_beu_utm_content","value":"__null__","domain":"www.samsung.com","path":"/","expires":1730292204,"size":24,"httpOnly":false,"secure":false,"session":false,"priority":"Medium","sameParty":false,"sourceScheme":"Secure"},{"name":"_ba_page_seq","value":"0","domain":"www.samsung.com","path":"/","expires":1730292204,"size":13,"httpOnly":false,"secure":false,"session":false,"priority":"Medium","sameParty":false,"sourceScheme":"Secure"},{"name":"__COM_SPEED","value":"H","domain":".samsung.com","path":"/","expires":1730376802.703235,"size":12,"httpOnly":false,"secure":false,"session":false,"priority":"Medium","sameParty":false,"sourceScheme":"Secure"},{"name":"_ba_ssid","value":"gMhCA9K0","domain":".samsung.com","path":"/","expires":1730292204,"size":16,"httpOnly":false,"secure":false,"session":false,"priority":"Medium","sameParty":false,"sourceScheme":"Secure"},{"name":"_gcl_au","value":"1.1.509512816.1730290408","domain":".samsung.com","path":"/","expires":1738066407,"size":31,"httpOnly":false,"secure":false,"session":false,"priority":"Medium","sameParty":false,"sourceScheme":"Secure"},{"name":"_ba_parent_seq","value":"0","domain":".samsung.com","path":"/","expires":1730292204,"size":15,"httpOnly":false,"secure":false,"session":false,"priority":"Medium","sameParty":false,"sourceScheme":"Secure"},{"name":"RT","value":"\"z=1&dm=samsung.com&si=9be2de5a-6dcc-46de-bb31-576e59e4f18f&ss=m2vu89r6&sl=1&tt=28c&bcn=%2F%2F684dd313.akstat.io%2F&ld=2in\"","domain":".samsung.com","path":"/","expires":1730895203,"size":125,"httpOnly":false,"secure":false,"session":false,"sameSite":"Lax","priority":"Medium","sameParty":false,"sourceScheme":"Secure"},{"name":"_beu_utm_campaign","value":"__null__","domain":"www.samsung.com","path":"/","expires":1730292204,"size":25,"httpOnly":false,"secure":false,"session":false,"priority":"Medium","sameParty":false,"sourceScheme":"Secure"},{"name":"cmapi_gtm_bl","value":"","domain":".samsung.com","path":"/","expires":1764418405,"size":12,"httpOnly":false,"secure":true,"session":false,"sameSite":"None","priority":"Medium","sameParty":false,"sourceScheme":"Secure"},{"name":"s_fpid","value":"09df1d1b-f9bd-49aa-8c6b-b577d385f27b","domain":".samsung.com","path":"/","expires":1764850401.980344,"size":42,"httpOnly":true,"secure":true,"session":false,"priority":"Medium","sameParty":false,"sourceScheme":"Secure"},{"name":"kndctr_470D362A62188DCD0A495F88_AdobeOrg_consent","value":"general%3Din","domain":".samsung.com","path":"/","expires":1745842407.426433,"size":60,"httpOnly":false,"secure":true,"session":false,"sameSite":"None","priority":"Medium","sameParty":false,"sourceScheme":"Secure"},{"name":"TAsessionID","value":"ed0e04d0-e4a7-4500-898d-2c246179dac3|NEW","domain":".samsung.com","path":"/","expires":1730292203,"size":51,"httpOnly":false,"secure":true,"session":false,"sameSite":"None","priority":"Medium","sameParty":false,"sourceScheme":"Secure"},{"name":"spr-chat-token-60ac299df7fbbc2eea3c5408_app_942679","value":"","domain":".samsung.com","path":"/","expires":-1,"size":50,"httpOnly":false,"secure":true,"session":true,"sameSite":"Strict","priority":"Medium","sameParty":false,"sourceScheme":"Secure"},{"name":"s_ppvl","value":"es%253Ahome%2C16%2C16%2C600%2C800%2C600%2C1920%2C1080%2C1%2CP","domain":"www.samsung.com","path":"/","expires":-1,"size":67,"httpOnly":false,"secure":false,"session":true,"priority":"Medium","sameParty":false,"sourceScheme":"Secure"},{"name":"s_pv","value":"es%3Ahome","domain":"www.samsung.com","path":"/","expires":1730292207,"size":13,"httpOnly":false,"secure":false,"session":false,"priority":"Medium","sameParty":false,"sourceScheme":"Secure"},{"name":"cookie_country","value":"es","domain":".samsung.com","path":"/","expires":1730376802,"size":16,"httpOnly":false,"secure":false,"session":false,"priority":"Medium","sameParty":false,"sourceScheme":"Secure"},{"name":"device_type","value":"pc","domain":".samsung.com","path":"/","expires":-1,"size":13,"httpOnly":false,"secure":false,"session":true,"priority":"Medium","sameParty":false,"sourceScheme":"Secure"},{"name":"kampyle_userid","value":"1574-a0be-b160-d8f7-341d-ae34-68ee-67e5","domain":"www.samsung.com","path":"/","expires":1761826406,"size":53,"httpOnly":false,"secure":true,"session":false,"sameSite":"None","priority":"Medium","sameParty":false,"sourceScheme":"Secure"},{"name":"_ba_rand","value":"74","domain":".samsung.com","path":"/","expires":1730292204,"size":10,"httpOnly":false,"secure":false,"session":false,"priority":"Medium","sameParty":false,"sourceScheme":"Secure"},{"name":"TAconsentID","value":"52a3dfc2-8312-4a37-9b30-8fe2582a424d","domain":".samsung.com","path":"/","expires":1764418405,"size":47,"httpOnly":false,"secure":true,"session":false,"sameSite":"None","priority":"Medium","sameParty":false,"sourceScheme":"Secure"}]